korean_text_matcher/__init__.py
korean_text_matcher/similarity_matcher.py
korean_text_matcher-0.2.0.dist-info/licenses/LICENSE
korean_text_matcher-0.2.0.dist-info/METADATA
korean_text_matcher-0.2.0.dist-info/WHEEL
korean_text_matcher-0.2.0.dist-info/top_level.txt
korean_text_matcher-0.2.0.dist-info/RECORD
