Metadata-Version: 2.4
Name: korean-text-matcher
Version: 0.2.0
Summary: A Python package for phonetic Korean text matching with enhanced first-character weighting.
Author-email: Kim Jeonhee <jeonhee.kim@powergen.ai>
Project-URL: Homepage, https://github.com/powergen5067/korean-text-matcher
Project-URL: Bug Tracker, https://github.com/powergen5067/korean-text-matcher/issues
Keywords: korean,text matching,similarity,한글,유사도,phonetic
Classifier: Programming Language :: Python :: 3
Classifier: License :: OSI Approved :: MIT License
Classifier: Operating System :: OS Independent
Classifier: Natural Language :: Korean
Classifier: Topic :: Text Processing
Classifier: Topic :: Scientific/Engineering :: Artificial Intelligence
Requires-Python: >=3.8
License-File: LICENSE
Dynamic: license-file
